sunanalysis/__init__.py
sunanalysis/sun_raytrace.py
sunanalysis/util.py
sunanalysis-0.0.7.dist-info/METADATA
sunanalysis-0.0.7.dist-info/WHEEL
sunanalysis-0.0.7.dist-info/licenses/LICENSE
sunanalysis-0.0.7.dist-info/RECORD
