Metadata-Version: 2.4
Name: sunanalysis
Version: 0.0.7
Summary: A package for sunanalysis
Project-URL: Homepage, https://github.com/pypa/sampleproject
Project-URL: Issues, https://github.com/pypa/sampleproject/issues
Author-email: chaogao <76209609@qq.com>
License-Expression: MIT
License-File: LICENSE
Classifier: License :: OSI Approved :: MIT License
Classifier: Operating System :: OS Independent
Classifier: Programming Language :: Python :: 3
Requires-Python: >=3.11
Requires-Dist: ladybug-core
Requires-Dist: rhino3dm
